[{"speciesAbbr": "CYGOLO", "breedingIndex": 30, "breedingCategory": 2}, {"speciesAbbr": "CYGCYG", "breedingIndex": 73, "breedingCategory": 4}, {"speciesAbbr": "ANAPEN", "breedingIndex": 73, "breedingCategory": 4}, {"speciesAbbr": "ANACRE", "breedingIndex": 73, "breedingCategory": 4}, {"speciesAbbr": "ANAPLA", "breedingIndex": 73, "breedingCategory": 4}, {"speciesAbbr": "ANAQUE", "breedingIndex": 20, "breedingCategory": 2}, {"speciesAbbr": "AYTFER", "breedingIndex": 50, "breedingCategory": 3}, {"speciesAbbr": "AYTFUL", "breedingIndex": 30, "breedingCategory": 2}, {"speciesAbbr": "BUCCLA", "breedingIndex": 82, "breedingCategory": 4}, {"speciesAbbr": "MERSER", "breedingIndex": 20, "breedingCategory": 2}, {"speciesAbbr": "MERMER", "breedingIndex": 30, "breedingCategory": 2}, {"speciesAbbr": "BONBON", "breedingIndex": 73, "breedingCategory": 4}, {"speciesAbbr": "TETRIX", "breedingIndex": 82, "breedingCategory": 4}, {"speciesAbbr": "TETURO", "breedingIndex": 40, "breedingCategory": 3}, {"speciesAbbr": "COTCOT", "breedingIndex": 40, "breedingCategory": 3}, {"speciesAbbr": "PHACOL", "breedingIndex": 73, "breedingCategory": 4}, {"speciesAbbr": "GAVARC", "breedingIndex": 73, "breedingCategory": 4}, {"speciesAbbr": "PODCRI", "breedingIndex": 75, "breedingCategory": 4}, {"speciesAbbr": "PODGRI", "breedingIndex": 20, "breedingCategory": 2}, {"speciesAbbr": "BOTSTE", "breedingIndex": 40, "breedingCategory": 3}, {"speciesAbbr": "ARDCIN", "breedingIndex": 20, "breedingCategory": 2}, {"speciesAbbr": "PERAPI", "breedingIndex": 66, "breedingCategory": 3}, {"speciesAbbr": "CIRAER", "breedingIndex": 74, "breedingCategory": 4}, {"speciesAbbr": "ACCGEN", "breedingIndex": 20, "breedingCategory": 2}, {"speciesAbbr": "ACCNIS", "breedingIndex": 82, "breedingCategory": 4}, {"speciesAbbr": "BUTBUT", "breedingIndex": 82, "breedingCategory": 4}, {"speciesAbbr": "FALTIN", "breedingIndex": 82, "breedingCategory": 4}, {"speciesAbbr": "FALCOL", "breedingIndex": 20, "breedingCategory": 2}, {"speciesAbbr": "FALSUB", "breedingIndex": 73, "breedingCategory": 4}, {"speciesAbbr": "RALAQU", "breedingIndex": 20, "breedingCategory": 2}, {"speciesAbbr": "PORPOR", "breedingIndex": 20, "breedingCategory": 2}, {"speciesAbbr": "CRECRE", "breedingIndex": 40, "breedingCategory": 3}, {"speciesAbbr": "GALCHL", "breedingIndex": 20, "breedingCategory": 2}, {"speciesAbbr": "FULATR", "breedingIndex": 75, "breedingCategory": 4}, {"speciesAbbr": "GRUGRU", "breedingIndex": 20, "breedingCategory": 2}, {"speciesAbbr": "HAEOST", "breedingIndex": 73, "breedingCategory": 4}, {"speciesAbbr": "CHADUB", "breedingIndex": 73, "breedingCategory": 4}, {"speciesAbbr": "VANVAN", "breedingIndex": 73, "breedingCategory": 4}, {"speciesAbbr": "GALGAL", "breedingIndex": 40, "breedingCategory": 3}, {"speciesAbbr": "SCORUS", "breedingIndex": 40, "breedingCategory": 3}, {"speciesAbbr": "NUMARQ", "breedingIndex": 63, "breedingCategory": 3}, {"speciesAbbr": "TRIOCH", "breedingIndex": 63, "breedingCategory": 3}, {"speciesAbbr": "TRIGLA", "breedingIndex": 20, "breedingCategory": 2}, {"speciesAbbr": "ACTHYP", "breedingIndex": 73, "breedingCategory": 4}, {"speciesAbbr": "LARRID", "breedingIndex": 30, "breedingCategory": 2}, {"speciesAbbr": "LARCAN", "breedingIndex": 73, "breedingCategory": 4}, {"speciesAbbr": "LARFUS", "breedingIndex": 20, "breedingCategory": 2}, {"speciesAbbr": "LARARG", "breedingIndex": 30, "breedingCategory": 2}, {"speciesAbbr": "STEHIR", "breedingIndex": 30, "breedingCategory": 2}, {"speciesAbbr": "COLLIV", "breedingIndex": 72, "breedingCategory": 4}, {"speciesAbbr": "COLOEN", "breedingIndex": 20, "breedingCategory": 2}, {"speciesAbbr": "COLPAL", "breedingIndex": 82, "breedingCategory": 4}, {"speciesAbbr": "STRDEC", "breedingIndex": 30, "breedingCategory": 2}, {"speciesAbbr": "CUCCAN", "breedingIndex": 40, "breedingCategory": 3}, {"speciesAbbr": "BUBBUB", "breedingIndex": 20, "breedingCategory": 2}, {"speciesAbbr": "GLAPAS", "breedingIndex": 20, "breedingCategory": 2}, {"speciesAbbr": "STRALU", "breedingIndex": 70, "breedingCategory": 4}, {"speciesAbbr": "ASIOTU", "breedingIndex": 73, "breedingCategory": 4}, {"speciesAbbr": "AEGFUN", "breedingIndex": 40, "breedingCategory": 3}, {"speciesAbbr": "CAPEUR", "breedingIndex": 40, "breedingCategory": 3}, {"speciesAbbr": "APUAPU", "breedingIndex": 60, "breedingCategory": 3}, {"speciesAbbr": "ALCATT", "breedingIndex": 72, "breedingCategory": 4}, {"speciesAbbr": "JYNTOR", "breedingIndex": 82, "breedingCategory": 4}, {"speciesAbbr": "PICCAN", "breedingIndex": 20, "breedingCategory": 2}, {"speciesAbbr": "DRYMAR", "breedingIndex": 81, "breedingCategory": 4}, {"speciesAbbr": "DENMAJ", "breedingIndex": 81, "breedingCategory": 4}, {"speciesAbbr": "DENLEU", "breedingIndex": 30, "breedingCategory": 2}, {"speciesAbbr": "DENMIN", "breedingIndex": 81, "breedingCategory": 4}, {"speciesAbbr": "PICTRI", "breedingIndex": 20, "breedingCategory": 2}, {"speciesAbbr": "LULARB", "breedingIndex": 63, "breedingCategory": 3}, {"speciesAbbr": "ALAARV", "breedingIndex": 20, "breedingCategory": 2}, {"speciesAbbr": "RIPRIP", "breedingIndex": 30, "breedingCategory": 2}, {"speciesAbbr": "HIRRUS", "breedingIndex": 73, "breedingCategory": 4}, {"speciesAbbr": "DELURB", "breedingIndex": 81, "breedingCategory": 4}, {"speciesAbbr": "ANTTRI", "breedingIndex": 82, "breedingCategory": 4}, {"speciesAbbr": "ANTPRA", "breedingIndex": 63, "breedingCategory": 3}, {"speciesAbbr": "MOTALB", "breedingIndex": 82, "breedingCategory": 4}, {"speciesAbbr": "TROTRO", "breedingIndex": 63, "breedingCategory": 3}, {"speciesAbbr": "PRUMOD", "breedingIndex": 73, "breedingCategory": 4}, {"speciesAbbr": "ERIRUB", "breedingIndex": 82, "breedingCategory": 4}, {"speciesAbbr": "LUSLUS", "breedingIndex": 82, "breedingCategory": 4}, {"speciesAbbr": "PHOOCH", "breedingIndex": 73, "breedingCategory": 4}, {"speciesAbbr": "PHOPHO", "breedingIndex": 82, "breedingCategory": 4}, {"speciesAbbr": "SAXRUB", "breedingIndex": 82, "breedingCategory": 4}, {"speciesAbbr": "OENOEN", "breedingIndex": 82, "breedingCategory": 4}, {"speciesAbbr": "TURMER", "breedingIndex": 82, "breedingCategory": 4}, {"speciesAbbr": "TURPIL", "breedingIndex": 82, "breedingCategory": 4}, {"speciesAbbr": "TURPHI", "breedingIndex": 82, "breedingCategory": 4}, {"speciesAbbr": "TURILI", "breedingIndex": 82, "breedingCategory": 4}, {"speciesAbbr": "TURVIS", "breedingIndex": 82, "breedingCategory": 4}, {"speciesAbbr": "LOCNAE", "breedingIndex": 40, "breedingCategory": 3}, {"speciesAbbr": "LOCFLU", "breedingIndex": 40, "breedingCategory": 3}, {"speciesAbbr": "ACRSCH", "breedingIndex": 82, "breedingCategory": 4}, {"speciesAbbr": "ACRSCI", "breedingIndex": 40, "breedingCategory": 3}, {"speciesAbbr": "ACRRIS", "breedingIndex": 40, "breedingCategory": 3}, {"speciesAbbr": "ACRDUM", "breedingIndex": 74, "breedingCategory": 4}, {"speciesAbbr": "HIPICT", "breedingIndex": 40, "breedingCategory": 3}, {"speciesAbbr": "SYLATR", "breedingIndex": 40, "breedingCategory": 3}, {"speciesAbbr": "SYLBOR", "breedingIndex": 82, "breedingCategory": 4}, {"speciesAbbr": "SYLCUR", "breedingIndex": 82, "breedingCategory": 4}, {"speciesAbbr": "SYLCOM", "breedingIndex": 73, "breedingCategory": 4}, {"speciesAbbr": "PHYDES", "breedingIndex": 20, "breedingCategory": 2}, {"speciesAbbr": "PHYSIB", "breedingIndex": 82, "breedingCategory": 4}, {"speciesAbbr": "PHYCOL", "breedingIndex": 82, "breedingCategory": 4}, {"speciesAbbr": "PHYLUS", "breedingIndex": 82, "breedingCategory": 4}, {"speciesAbbr": "REGREG", "breedingIndex": 81, "breedingCategory": 4}, {"speciesAbbr": "MUSSTR", "breedingIndex": 82, "breedingCategory": 4}, {"speciesAbbr": "FICPAR", "breedingIndex": 20, "breedingCategory": 2}, {"speciesAbbr": "FICHYP", "breedingIndex": 82, "breedingCategory": 4}, {"speciesAbbr": "PANBIA", "breedingIndex": 20, "breedingCategory": 2}, {"speciesAbbr": "AEGCAU", "breedingIndex": 73, "breedingCategory": 4}, {"speciesAbbr": "PARMON", "breedingIndex": 82, "breedingCategory": 4}, {"speciesAbbr": "PARCRI", "breedingIndex": 82, "breedingCategory": 4}, {"speciesAbbr": "PARATE", "breedingIndex": 82, "breedingCategory": 4}, {"speciesAbbr": "PARCAE", "breedingIndex": 82, "breedingCategory": 4}, {"speciesAbbr": "PARMAJ", "breedingIndex": 82, "breedingCategory": 4}, {"speciesAbbr": "SITEUR", "breedingIndex": 20, "breedingCategory": 2}, {"speciesAbbr": "CERFAM", "breedingIndex": 82, "breedingCategory": 4}, {"speciesAbbr": "ORIORI", "breedingIndex": 20, "breedingCategory": 2}, {"speciesAbbr": "LANCOL", "breedingIndex": 73, "breedingCategory": 4}, {"speciesAbbr": "GARGLA", "breedingIndex": 82, "breedingCategory": 4}, {"speciesAbbr": "PICPIC", "breedingIndex": 82, "breedingCategory": 4}, {"speciesAbbr": "CORMON", "breedingIndex": 72, "breedingCategory": 4}, {"speciesAbbr": "CORNIX", "breedingIndex": 62, "breedingCategory": 3}, {"speciesAbbr": "STUVUL", "breedingIndex": 82, "breedingCategory": 4}, {"speciesAbbr": "PASDOM", "breedingIndex": 73, "breedingCategory": 4}, {"speciesAbbr": "PASMON", "breedingIndex": 82, "breedingCategory": 4}, {"speciesAbbr": "FRICOE", "breedingIndex": 82, "breedingCategory": 4}, {"speciesAbbr": "CARCHL", "breedingIndex": 82, "breedingCategory": 4}, {"speciesAbbr": "CARCAR", "breedingIndex": 82, "breedingCategory": 4}, {"speciesAbbr": "CARSPI", "breedingIndex": 40, "breedingCategory": 3}, {"speciesAbbr": "CARCAN", "breedingIndex": 73, "breedingCategory": 4}, {"speciesAbbr": "LOXCUR", "breedingIndex": 20, "breedingCategory": 2}, {"speciesAbbr": "LOXPYT", "breedingIndex": 81, "breedingCategory": 4}, {"speciesAbbr": "CARERY", "breedingIndex": 63, "breedingCategory": 3}, {"speciesAbbr": "PYRPYR", "breedingIndex": 73, "breedingCategory": 4}, {"speciesAbbr": "EMBCIT", "breedingIndex": 82, "breedingCategory": 4}, {"speciesAbbr": "EMBHOR", "breedingIndex": 40, "breedingCategory": 3}, {"speciesAbbr": "EMBSCH", "breedingIndex": 82, "breedingCategory": 4}]