[{"speciesAbbr": "CYGCYG", "breedingIndex": 30, "breedingCategory": 2}, {"speciesAbbr": "ANAPEN", "breedingIndex": 73, "breedingCategory": 4}, {"speciesAbbr": "ANACRE", "breedingIndex": 30, "breedingCategory": 2}, {"speciesAbbr": "ANAPLA", "breedingIndex": 73, "breedingCategory": 4}, {"speciesAbbr": "ANAACU", "breedingIndex": 73, "breedingCategory": 4}, {"speciesAbbr": "BUCCLA", "breedingIndex": 71, "breedingCategory": 4}, {"speciesAbbr": "BONBON", "breedingIndex": 82, "breedingCategory": 4}, {"speciesAbbr": "TETRIX", "breedingIndex": 73, "breedingCategory": 4}, {"speciesAbbr": "TETURO", "breedingIndex": 73, "breedingCategory": 4}, {"speciesAbbr": "COTCOT", "breedingIndex": 40, "breedingCategory": 3}, {"speciesAbbr": "PHACOL", "breedingIndex": 40, "breedingCategory": 3}, {"speciesAbbr": "CIRCYA", "breedingIndex": 40, "breedingCategory": 3}, {"speciesAbbr": "ACCNIS", "breedingIndex": 81, "breedingCategory": 4}, {"speciesAbbr": "FALTIN", "breedingIndex": 30, "breedingCategory": 2}, {"speciesAbbr": "FALSUB", "breedingIndex": 63, "breedingCategory": 3}, {"speciesAbbr": "CRECRE", "breedingIndex": 40, "breedingCategory": 3}, {"speciesAbbr": "GRUGRU", "breedingIndex": 50, "breedingCategory": 3}, {"speciesAbbr": "CHADUB", "breedingIndex": 50, "breedingCategory": 3}, {"speciesAbbr": "VANVAN", "breedingIndex": 73, "breedingCategory": 4}, {"speciesAbbr": "GALGAL", "breedingIndex": 63, "breedingCategory": 3}, {"speciesAbbr": "SCORUS", "breedingIndex": 40, "breedingCategory": 3}, {"speciesAbbr": "NUMPHA", "breedingIndex": 20, "breedingCategory": 2}, {"speciesAbbr": "NUMARQ", "breedingIndex": 73, "breedingCategory": 4}, {"speciesAbbr": "TRINEB", "breedingIndex": 63, "breedingCategory": 3}, {"speciesAbbr": "TRIOCH", "breedingIndex": 63, "breedingCategory": 3}, {"speciesAbbr": "TRIGLA", "breedingIndex": 63, "breedingCategory": 3}, {"speciesAbbr": "ACTHYP", "breedingIndex": 20, "breedingCategory": 2}, {"speciesAbbr": "LARRID", "breedingIndex": 73, "breedingCategory": 4}, {"speciesAbbr": "LARCAN", "breedingIndex": 63, "breedingCategory": 3}, {"speciesAbbr": "STEHIR", "breedingIndex": 30, "breedingCategory": 2}, {"speciesAbbr": "COLPAL", "breedingIndex": 73, "breedingCategory": 4}, {"speciesAbbr": "CUCCAN", "breedingIndex": 40, "breedingCategory": 3}, {"speciesAbbr": "BUBBUB", "breedingIndex": 20, "breedingCategory": 2}, {"speciesAbbr": "STRURA", "breedingIndex": 30, "breedingCategory": 2}, {"speciesAbbr": "ASIOTU", "breedingIndex": 20, "breedingCategory": 2}, {"speciesAbbr": "AEGFUN", "breedingIndex": 20, "breedingCategory": 2}, {"speciesAbbr": "APUAPU", "breedingIndex": 72, "breedingCategory": 4}, {"speciesAbbr": "JYNTOR", "breedingIndex": 20, "breedingCategory": 2}, {"speciesAbbr": "DRYMAR", "breedingIndex": 80, "breedingCategory": 4}, {"speciesAbbr": "DENMAJ", "breedingIndex": 81, "breedingCategory": 4}, {"speciesAbbr": "DENMIN", "breedingIndex": 20, "breedingCategory": 2}, {"speciesAbbr": "ALAARV", "breedingIndex": 50, "breedingCategory": 3}, {"speciesAbbr": "HIRRUS", "breedingIndex": 82, "breedingCategory": 4}, {"speciesAbbr": "DELURB", "breedingIndex": 72, "breedingCategory": 4}, {"speciesAbbr": "ANTTRI", "breedingIndex": 63, "breedingCategory": 3}, {"speciesAbbr": "ANTPRA", "breedingIndex": 74, "breedingCategory": 4}, {"speciesAbbr": "MOTFLA", "breedingIndex": 20, "breedingCategory": 2}, {"speciesAbbr": "MOTALB", "breedingIndex": 74, "breedingCategory": 4}, {"speciesAbbr": "PRUMOD", "breedingIndex": 63, "breedingCategory": 3}, {"speciesAbbr": "ERIRUB", "breedingIndex": 50, "breedingCategory": 3}, {"speciesAbbr": "LUSLUS", "breedingIndex": 40, "breedingCategory": 3}, {"speciesAbbr": "PHOPHO", "breedingIndex": 63, "breedingCategory": 3}, {"speciesAbbr": "SAXRUB", "breedingIndex": 74, "breedingCategory": 4}, {"speciesAbbr": "TURMER", "breedingIndex": 82, "breedingCategory": 4}, {"speciesAbbr": "TURPIL", "breedingIndex": 82, "breedingCategory": 4}, {"speciesAbbr": "TURPHI", "breedingIndex": 73, "breedingCategory": 4}, {"speciesAbbr": "TURILI", "breedingIndex": 74, "breedingCategory": 4}, {"speciesAbbr": "TURVIS", "breedingIndex": 20, "breedingCategory": 2}, {"speciesAbbr": "ACRSCH", "breedingIndex": 74, "breedingCategory": 4}, {"speciesAbbr": "ACRDUM", "breedingIndex": 63, "breedingCategory": 3}, {"speciesAbbr": "SYLBOR", "breedingIndex": 74, "breedingCategory": 4}, {"speciesAbbr": "SYLCUR", "breedingIndex": 40, "breedingCategory": 3}, {"speciesAbbr": "SYLCOM", "breedingIndex": 63, "breedingCategory": 3}, {"speciesAbbr": "PHYSIB", "breedingIndex": 20, "breedingCategory": 2}, {"speciesAbbr": "PHYCOL", "breedingIndex": 63, "breedingCategory": 3}, {"speciesAbbr": "PHYLUS", "breedingIndex": 74, "breedingCategory": 4}, {"speciesAbbr": "REGREG", "breedingIndex": 50, "breedingCategory": 3}, {"speciesAbbr": "MUSSTR", "breedingIndex": 73, "breedingCategory": 4}, {"speciesAbbr": "FICHYP", "breedingIndex": 72, "breedingCategory": 4}, {"speciesAbbr": "PARMON", "breedingIndex": 73, "breedingCategory": 4}, {"speciesAbbr": "PARCRI", "breedingIndex": 30, "breedingCategory": 2}, {"speciesAbbr": "PARCAE", "breedingIndex": 74, "breedingCategory": 4}, {"speciesAbbr": "PARMAJ", "breedingIndex": 82, "breedingCategory": 4}, {"speciesAbbr": "CERFAM", "breedingIndex": 74, "breedingCategory": 4}, {"speciesAbbr": "LANCOL", "breedingIndex": 63, "breedingCategory": 3}, {"speciesAbbr": "LANEXC", "breedingIndex": 82, "breedingCategory": 4}, {"speciesAbbr": "GARGLA", "breedingIndex": 73, "breedingCategory": 4}, {"speciesAbbr": "PICPIC", "breedingIndex": 73, "breedingCategory": 4}, {"speciesAbbr": "CORMON", "breedingIndex": 60, "breedingCategory": 3}, {"speciesAbbr": "CORNIX", "breedingIndex": 73, "breedingCategory": 4}, {"speciesAbbr": "CORRAX", "breedingIndex": 20, "breedingCategory": 2}, {"speciesAbbr": "PASDOM", "breedingIndex": 72, "breedingCategory": 4}, {"speciesAbbr": "FRICOE", "breedingIndex": 74, "breedingCategory": 4}, {"speciesAbbr": "FRIMON", "breedingIndex": 20, "breedingCategory": 2}, {"speciesAbbr": "CARCHL", "breedingIndex": 82, "breedingCategory": 4}, {"speciesAbbr": "CARSPI", "breedingIndex": 63, "breedingCategory": 3}, {"speciesAbbr": "CARERY", "breedingIndex": 74, "breedingCategory": 4}, {"speciesAbbr": "EMBCIT", "breedingIndex": 63, "breedingCategory": 3}, {"speciesAbbr": "EMBSCH", "breedingIndex": 74, "breedingCategory": 4}]