[{"speciesAbbr": "CYGCYG", "breedingIndex": 75, "breedingCategory": 4}, {"speciesAbbr": "ANACRE", "breedingIndex": 30, "breedingCategory": 2}, {"speciesAbbr": "ANAPLA", "breedingIndex": 73, "breedingCategory": 4}, {"speciesAbbr": "AYTFUL", "breedingIndex": 73, "breedingCategory": 4}, {"speciesAbbr": "BUCCLA", "breedingIndex": 30, "breedingCategory": 2}, {"speciesAbbr": "BONBON", "breedingIndex": 73, "breedingCategory": 4}, {"speciesAbbr": "LAGLAG", "breedingIndex": 30, "breedingCategory": 2}, {"speciesAbbr": "TETRIX", "breedingIndex": 40, "breedingCategory": 3}, {"speciesAbbr": "GAVSTE", "breedingIndex": 30, "breedingCategory": 2}, {"speciesAbbr": "PERAPI", "breedingIndex": 30, "breedingCategory": 2}, {"speciesAbbr": "ACCGEN", "breedingIndex": 20, "breedingCategory": 2}, {"speciesAbbr": "PANHAL", "breedingIndex": 82, "breedingCategory": 4}, {"speciesAbbr": "FALTIN", "breedingIndex": 73, "breedingCategory": 4}, {"speciesAbbr": "CRECRE", "breedingIndex": 20, "breedingCategory": 2}, {"speciesAbbr": "GRUGRU", "breedingIndex": 73, "breedingCategory": 4}, {"speciesAbbr": "VANVAN", "breedingIndex": 63, "breedingCategory": 3}, {"speciesAbbr": "PHIPUG", "breedingIndex": 50, "breedingCategory": 3}, {"speciesAbbr": "GALGAL", "breedingIndex": 40, "breedingCategory": 3}, {"speciesAbbr": "NUMPHA", "breedingIndex": 63, "breedingCategory": 3}, {"speciesAbbr": "NUMARQ", "breedingIndex": 63, "breedingCategory": 3}, {"speciesAbbr": "TRIERY", "breedingIndex": 40, "breedingCategory": 3}, {"speciesAbbr": "TRINEB", "breedingIndex": 63, "breedingCategory": 3}, {"speciesAbbr": "TRIOCH", "breedingIndex": 63, "breedingCategory": 3}, {"speciesAbbr": "TRIGLA", "breedingIndex": 81, "breedingCategory": 4}, {"speciesAbbr": "ACTHYP", "breedingIndex": 20, "breedingCategory": 2}, {"speciesAbbr": "LARMIN", "breedingIndex": 20, "breedingCategory": 2}, {"speciesAbbr": "LARRID", "breedingIndex": 63, "breedingCategory": 3}, {"speciesAbbr": "LARCAN", "breedingIndex": 30, "breedingCategory": 2}, {"speciesAbbr": "LARFUS", "breedingIndex": 20, "breedingCategory": 2}, {"speciesAbbr": "STEHIR", "breedingIndex": 63, "breedingCategory": 3}, {"speciesAbbr": "COLPAL", "breedingIndex": 30, "breedingCategory": 2}, {"speciesAbbr": "CUCCAN", "breedingIndex": 40, "breedingCategory": 3}, {"speciesAbbr": "APUAPU", "breedingIndex": 40, "breedingCategory": 3}, {"speciesAbbr": "DENMAJ", "breedingIndex": 20, "breedingCategory": 2}, {"speciesAbbr": "RIPRIP", "breedingIndex": 72, "breedingCategory": 4}, {"speciesAbbr": "HIRRUS", "breedingIndex": 72, "breedingCategory": 4}, {"speciesAbbr": "DELURB", "breedingIndex": 73, "breedingCategory": 4}, {"speciesAbbr": "ANTTRI", "breedingIndex": 60, "breedingCategory": 3}, {"speciesAbbr": "ANTPRA", "breedingIndex": 74, "breedingCategory": 4}, {"speciesAbbr": "MOTFLA", "breedingIndex": 74, "breedingCategory": 4}, {"speciesAbbr": "MOTALB", "breedingIndex": 74, "breedingCategory": 4}, {"speciesAbbr": "BOMGAR", "breedingIndex": 20, "breedingCategory": 2}, {"speciesAbbr": "ERIRUB", "breedingIndex": 73, "breedingCategory": 4}, {"speciesAbbr": "TARCYA", "breedingIndex": 40, "breedingCategory": 3}, {"speciesAbbr": "PHOPHO", "breedingIndex": 63, "breedingCategory": 3}, {"speciesAbbr": "SAXRUB", "breedingIndex": 74, "breedingCategory": 4}, {"speciesAbbr": "TURPIL", "breedingIndex": 63, "breedingCategory": 3}, {"speciesAbbr": "TURPHI", "breedingIndex": 73, "breedingCategory": 4}, {"speciesAbbr": "TURILI", "breedingIndex": 20, "breedingCategory": 2}, {"speciesAbbr": "TURVIS", "breedingIndex": 20, "breedingCategory": 2}, {"speciesAbbr": "ACRSCH", "breedingIndex": 20, "breedingCategory": 2}, {"speciesAbbr": "SYLBOR", "breedingIndex": 60, "breedingCategory": 3}, {"speciesAbbr": "SYLCUR", "breedingIndex": 20, "breedingCategory": 2}, {"speciesAbbr": "SYLCOM", "breedingIndex": 20, "breedingCategory": 2}, {"speciesAbbr": "PHYCOL", "breedingIndex": 20, "breedingCategory": 2}, {"speciesAbbr": "PHYLUS", "breedingIndex": 81, "breedingCategory": 4}, {"speciesAbbr": "REGREG", "breedingIndex": 73, "breedingCategory": 4}, {"speciesAbbr": "MUSSTR", "breedingIndex": 63, "breedingCategory": 3}, {"speciesAbbr": "FICHYP", "breedingIndex": 30, "breedingCategory": 2}, {"speciesAbbr": "PARMON", "breedingIndex": 73, "breedingCategory": 4}, {"speciesAbbr": "PARCRI", "breedingIndex": 20, "breedingCategory": 2}, {"speciesAbbr": "PARCAE", "breedingIndex": 20, "breedingCategory": 2}, {"speciesAbbr": "PARMAJ", "breedingIndex": 73, "breedingCategory": 4}, {"speciesAbbr": "CERFAM", "breedingIndex": 20, "breedingCategory": 2}, {"speciesAbbr": "GARGLA", "breedingIndex": 73, "breedingCategory": 4}, {"speciesAbbr": "PICPIC", "breedingIndex": 63, "breedingCategory": 3}, {"speciesAbbr": "CORNIX", "breedingIndex": 20, "breedingCategory": 2}, {"speciesAbbr": "CORRAX", "breedingIndex": 20, "breedingCategory": 2}, {"speciesAbbr": "PASDOM", "breedingIndex": 61, "breedingCategory": 3}, {"speciesAbbr": "FRICOE", "breedingIndex": 74, "breedingCategory": 4}, {"speciesAbbr": "FRIMON", "breedingIndex": 63, "breedingCategory": 3}, {"speciesAbbr": "CARCHL", "breedingIndex": 30, "breedingCategory": 2}, {"speciesAbbr": "CARSPI", "breedingIndex": 73, "breedingCategory": 4}, {"speciesAbbr": "LOXCUR", "breedingIndex": 20, "breedingCategory": 2}, {"speciesAbbr": "CARERY", "breedingIndex": 20, "breedingCategory": 2}, {"speciesAbbr": "PYRPYR", "breedingIndex": 30, "breedingCategory": 2}, {"speciesAbbr": "EMBCIT", "breedingIndex": 60, "breedingCategory": 3}, {"speciesAbbr": "EMBRUS", "breedingIndex": 63, "breedingCategory": 3}, {"speciesAbbr": "EMBSCH", "breedingIndex": 60, "breedingCategory": 3}]