[{"speciesAbbr": "CYGCYG", "breedingIndex": 60, "breedingCategory": 3}, {"speciesAbbr": "ANSFAB", "breedingIndex": 60, "breedingCategory": 3}, {"speciesAbbr": "ANAPEN", "breedingIndex": 30, "breedingCategory": 2}, {"speciesAbbr": "ANACRE", "breedingIndex": 73, "breedingCategory": 4}, {"speciesAbbr": "ANAPLA", "breedingIndex": 40, "breedingCategory": 3}, {"speciesAbbr": "AYTFUL", "breedingIndex": 50, "breedingCategory": 3}, {"speciesAbbr": "MELNIG", "breedingIndex": 20, "breedingCategory": 2}, {"speciesAbbr": "BUCCLA", "breedingIndex": 73, "breedingCategory": 4}, {"speciesAbbr": "MERALB", "breedingIndex": 73, "breedingCategory": 4}, {"speciesAbbr": "MERSER", "breedingIndex": 30, "breedingCategory": 2}, {"speciesAbbr": "MERMER", "breedingIndex": 50, "breedingCategory": 3}, {"speciesAbbr": "LAGLAG", "breedingIndex": 20, "breedingCategory": 2}, {"speciesAbbr": "TETRIX", "breedingIndex": 73, "breedingCategory": 4}, {"speciesAbbr": "TETURO", "breedingIndex": 73, "breedingCategory": 4}, {"speciesAbbr": "GAVARC", "breedingIndex": 30, "breedingCategory": 2}, {"speciesAbbr": "CIRCYA", "breedingIndex": 30, "breedingCategory": 2}, {"speciesAbbr": "ACCNIS", "breedingIndex": 20, "breedingCategory": 2}, {"speciesAbbr": "BUTLAG", "breedingIndex": 40, "breedingCategory": 3}, {"speciesAbbr": "FALCOL", "breedingIndex": 20, "breedingCategory": 2}, {"speciesAbbr": "GRUGRU", "breedingIndex": 60, "breedingCategory": 3}, {"speciesAbbr": "CHAHIA", "breedingIndex": 63, "breedingCategory": 3}, {"speciesAbbr": "LIMFAL", "breedingIndex": 63, "breedingCategory": 3}, {"speciesAbbr": "PHIPUG", "breedingIndex": 64, "breedingCategory": 3}, {"speciesAbbr": "LYMMIN", "breedingIndex": 20, "breedingCategory": 2}, {"speciesAbbr": "GALGAL", "breedingIndex": 60, "breedingCategory": 3}, {"speciesAbbr": "TRIERY", "breedingIndex": 60, "breedingCategory": 3}, {"speciesAbbr": "TRINEB", "breedingIndex": 63, "breedingCategory": 3}, {"speciesAbbr": "TRIOCH", "breedingIndex": 10, "breedingCategory": 1}, {"speciesAbbr": "TRIGLA", "breedingIndex": 73, "breedingCategory": 4}, {"speciesAbbr": "ACTHYP", "breedingIndex": 63, "breedingCategory": 3}, {"speciesAbbr": "PHALOB", "breedingIndex": 20, "breedingCategory": 2}, {"speciesAbbr": "LARCAN", "breedingIndex": 30, "breedingCategory": 2}, {"speciesAbbr": "LARARG", "breedingIndex": 20, "breedingCategory": 2}, {"speciesAbbr": "LARMAR", "breedingIndex": 10, "breedingCategory": 1}, {"speciesAbbr": "COLPAL", "breedingIndex": 20, "breedingCategory": 2}, {"speciesAbbr": "CUCCAN", "breedingIndex": 20, "breedingCategory": 2}, {"speciesAbbr": "SURULU", "breedingIndex": 20, "breedingCategory": 2}, {"speciesAbbr": "DENMAJ", "breedingIndex": 20, "breedingCategory": 2}, {"speciesAbbr": "RIPRIP", "breedingIndex": 20, "breedingCategory": 2}, {"speciesAbbr": "HIRRUS", "breedingIndex": 20, "breedingCategory": 2}, {"speciesAbbr": "DELURB", "breedingIndex": 70, "breedingCategory": 4}, {"speciesAbbr": "ANTTRI", "breedingIndex": 60, "breedingCategory": 3}, {"speciesAbbr": "ANTPRA", "breedingIndex": 74, "breedingCategory": 4}, {"speciesAbbr": "MOTFLA", "breedingIndex": 74, "breedingCategory": 4}, {"speciesAbbr": "MOTALB", "breedingIndex": 73, "breedingCategory": 4}, {"speciesAbbr": "BOMGAR", "breedingIndex": 30, "breedingCategory": 2}, {"speciesAbbr": "PHOPHO", "breedingIndex": 60, "breedingCategory": 3}, {"speciesAbbr": "SAXRUB", "breedingIndex": 73, "breedingCategory": 4}, {"speciesAbbr": "TURPIL", "breedingIndex": 73, "breedingCategory": 4}, {"speciesAbbr": "TURPHI", "breedingIndex": 73, "breedingCategory": 4}, {"speciesAbbr": "TURILI", "breedingIndex": 82, "breedingCategory": 4}, {"speciesAbbr": "TURVIS", "breedingIndex": 40, "breedingCategory": 3}, {"speciesAbbr": "ACRSCH", "breedingIndex": 60, "breedingCategory": 3}, {"speciesAbbr": "PHYLUS", "breedingIndex": 74, "breedingCategory": 4}, {"speciesAbbr": "MUSSTR", "breedingIndex": 60, "breedingCategory": 3}, {"speciesAbbr": "PARCIN", "breedingIndex": 20, "breedingCategory": 2}, {"speciesAbbr": "PARMAJ", "breedingIndex": 20, "breedingCategory": 2}, {"speciesAbbr": "LANEXC", "breedingIndex": 20, "breedingCategory": 2}, {"speciesAbbr": "PERINF", "breedingIndex": 73, "breedingCategory": 4}, {"speciesAbbr": "PICPIC", "breedingIndex": 20, "breedingCategory": 2}, {"speciesAbbr": "CORNIX", "breedingIndex": 60, "breedingCategory": 3}, {"speciesAbbr": "CORRAX", "breedingIndex": 73, "breedingCategory": 4}, {"speciesAbbr": "FRICOE", "breedingIndex": 63, "breedingCategory": 3}, {"speciesAbbr": "FRIMON", "breedingIndex": 63, "breedingCategory": 3}, {"speciesAbbr": "CARCHL", "breedingIndex": 40, "breedingCategory": 3}, {"speciesAbbr": "CARSPI", "breedingIndex": 73, "breedingCategory": 4}, {"speciesAbbr": "CARMEA", "breedingIndex": 73, "breedingCategory": 4}, {"speciesAbbr": "LOXCUR", "breedingIndex": 20, "breedingCategory": 2}, {"speciesAbbr": "PYRPYR", "breedingIndex": 30, "breedingCategory": 2}, {"speciesAbbr": "EMBCIT", "breedingIndex": 20, "breedingCategory": 2}, {"speciesAbbr": "EMBRUS", "breedingIndex": 60, "breedingCategory": 3}, {"speciesAbbr": "EMBPUS", "breedingIndex": 73, "breedingCategory": 4}, {"speciesAbbr": "EMBSCH", "breedingIndex": 73, "breedingCategory": 4}]