{"laulujoutsen": {"speciesAbbr": "CYGCYG", "breedingIndex": 30, "breedingCategory": 2, "speciesFi": "laulujoutsen"}, "haapana": {"speciesAbbr": "ANAPEN", "breedingIndex": 73, "breedingCategory": 4, "speciesFi": "haapana"}, "sinisorsa": {"speciesAbbr": "ANAPLA", "breedingIndex": 20, "breedingCategory": 2, "speciesFi": "sinisorsa"}, "telkkä": {"speciesAbbr": "BUCCLA", "breedingIndex": 73, "breedingCategory": 4, "speciesFi": "telkkä"}, "riekko": {"speciesAbbr": "LAGLAG", "breedingIndex": 73, "breedingCategory": 4, "speciesFi": "riekko"}, "teeri": {"speciesAbbr": "TETRIX", "breedingIndex": 73, "breedingCategory": 4, "speciesFi": "teeri"}, "metso": {"speciesAbbr": "TETURO", "breedingIndex": 20, "breedingCategory": 2, "speciesFi": "metso"}, "sinisuohaukka": {"speciesAbbr": "CIRCYA", "breedingIndex": 73, "breedingCategory": 4, "speciesFi": "sinisuohaukka"}, "kanahaukka": {"speciesAbbr": "ACCGEN", "breedingIndex": 20, "breedingCategory": 2, "speciesFi": "kanahaukka"}, "hiirihaukka": {"speciesAbbr": "BUTBUT", "breedingIndex": 20, "breedingCategory": 2, "speciesFi": "hiirihaukka"}, "tuulihaukka": {"speciesAbbr": "FALTIN", "breedingIndex": 20, "breedingCategory": 2, "speciesFi": "tuulihaukka"}, "kurki": {"speciesAbbr": "GRUGRU", "breedingIndex": 30, "breedingCategory": 2, "speciesFi": "kurki"}, "lapinsirri": {"speciesAbbr": "CALTEM", "breedingIndex": 30, "breedingCategory": 2, "speciesFi": "lapinsirri"}, "pikkukuovi": {"speciesAbbr": "NUMPHA", "breedingIndex": 63, "breedingCategory": 3, "speciesFi": "pikkukuovi"}, "kuovi": {"speciesAbbr": "NUMARQ", "breedingIndex": 30, "breedingCategory": 2, "speciesFi": "kuovi"}, "valkoviklo": {"speciesAbbr": "TRINEB", "breedingIndex": 20, "breedingCategory": 2, "speciesFi": "valkoviklo"}, "liro": {"speciesAbbr": "TRIGLA", "breedingIndex": 73, "breedingCategory": 4, "speciesFi": "liro"}, "rantasipi": {"speciesAbbr": "ACTHYP", "breedingIndex": 73, "breedingCategory": 4, "speciesFi": "rantasipi"}, "naurulokki": {"speciesAbbr": "LARRID", "breedingIndex": 20, "breedingCategory": 2, "speciesFi": "naurulokki"}, "kalalokki": {"speciesAbbr": "LARCAN", "breedingIndex": 75, "breedingCategory": 4, "speciesFi": "kalalokki"}, "harmaalokki": {"speciesAbbr": "LARARG", "breedingIndex": 30, "breedingCategory": 2, "speciesFi": "harmaalokki"}, "merilokki": {"speciesAbbr": "LARMAR", "breedingIndex": 30, "breedingCategory": 2, "speciesFi": "merilokki"}, "lapintiira": {"speciesAbbr": "STEAEA", "breedingIndex": 61, "breedingCategory": 3, "speciesFi": "lapintiira"}, "hiiripöllö": {"speciesAbbr": "SURULU", "breedingIndex": 63, "breedingCategory": 3, "speciesFi": "hiiripöllö"}, "tervapääsky": {"speciesAbbr": "APUAPU", "breedingIndex": 61, "breedingCategory": 3, "speciesFi": "tervapääsky"}, "käpytikka": {"speciesAbbr": "DENMAJ", "breedingIndex": 81, "breedingCategory": 4, "speciesFi": "käpytikka"}, "metsäkirvinen": {"speciesAbbr": "ANTTRI", "breedingIndex": 73, "breedingCategory": 4, "speciesFi": "metsäkirvinen"}, "niittykirvinen": {"speciesAbbr": "ANTPRA", "breedingIndex": 73, "breedingCategory": 4, "speciesFi": "niittykirvinen"}, "keltavästäräkki": {"speciesAbbr": "MOTFLA", "breedingIndex": 73, "breedingCategory": 4, "speciesFi": "keltavästäräkki"}, "västäräkki": {"speciesAbbr": "MOTALB", "breedingIndex": 73, "breedingCategory": 4, "speciesFi": "västäräkki"}, "tilhi": {"speciesAbbr": "BOMGAR", "breedingIndex": 20, "breedingCategory": 2, "speciesFi": "tilhi"}, "sinirinta": {"speciesAbbr": "LUSSVE", "breedingIndex": 73, "breedingCategory": 4, "speciesFi": "sinirinta"}, "leppälintu": {"speciesAbbr": "PHOPHO", "breedingIndex": 73, "breedingCategory": 4, "speciesFi": "leppälintu"}, "kivitasku": {"speciesAbbr": "OENOEN", "breedingIndex": 73, "breedingCategory": 4, "speciesFi": "kivitasku"}, "räkättirastas": {"speciesAbbr": "TURPIL", "breedingIndex": 73, "breedingCategory": 4, "speciesFi": "räkättirastas"}, "punakylkirastas": {"speciesAbbr": "TURILI", "breedingIndex": 74, "breedingCategory": 4, "speciesFi": "punakylkirastas"}, "kulorastas": {"speciesAbbr": "TURVIS", "breedingIndex": 73, "breedingCategory": 4, "speciesFi": "kulorastas"}, "pajulintu": {"speciesAbbr": "PHYLUS", "breedingIndex": 74, "breedingCategory": 4, "speciesFi": "pajulintu"}, "harmaasieppo": {"speciesAbbr": "MUSSTR", "breedingIndex": 73, "breedingCategory": 4, "speciesFi": "harmaasieppo"}, "hömötiainen": {"speciesAbbr": "PARMON", "breedingIndex": 73, "breedingCategory": 4, "speciesFi": "hömötiainen"}, "lapintiainen": {"speciesAbbr": "PARCIN", "breedingIndex": 73, "breedingCategory": 4, "speciesFi": "lapintiainen"}, "talitiainen": {"speciesAbbr": "PARMAJ", "breedingIndex": 73, "breedingCategory": 4, "speciesFi": "talitiainen"}, "isolepinkäinen": {"speciesAbbr": "LANEXC", "breedingIndex": 73, "breedingCategory": 4, "speciesFi": "isolepinkäinen"}, "kuukkeli": {"speciesAbbr": "PERINF", "breedingIndex": 73, "breedingCategory": 4, "speciesFi": "kuukkeli"}, "harakka": {"speciesAbbr": "PICPIC", "breedingIndex": 62, "breedingCategory": 3, "speciesFi": "harakka"}, "varis": {"speciesAbbr": "CORNIX", "breedingIndex": 73, "breedingCategory": 4, "speciesFi": "varis"}, "korppi": {"speciesAbbr": "CORRAX", "breedingIndex": 73, "breedingCategory": 4, "speciesFi": "korppi"}, "peippo": {"speciesAbbr": "FRICOE", "breedingIndex": 20, "breedingCategory": 2, "speciesFi": "peippo"}, "järripeippo": {"speciesAbbr": "FRIMON", "breedingIndex": 73, "breedingCategory": 4, "speciesFi": "järripeippo"}, "vihervarpunen": {"speciesAbbr": "CARSPI", "breedingIndex": 73, "breedingCategory": 4, "speciesFi": "vihervarpunen"}, "urpiainen": {"speciesAbbr": "CARMEA", "breedingIndex": 73, "breedingCategory": 4, "speciesFi": "urpiainen"}, "pikkukäpylintu": {"speciesAbbr": "LOXCUR", "breedingIndex": 73, "breedingCategory": 4, "speciesFi": "pikkukäpylintu"}, "taviokuurna": {"speciesAbbr": "PINENU", "breedingIndex": 30, "breedingCategory": 2, "speciesFi": "taviokuurna"}, "pikkusirkku": {"speciesAbbr": "EMBPUS", "breedingIndex": 20, "breedingCategory": 2, "speciesFi": "pikkusirkku"}, "pajusirkku": {"speciesAbbr": "EMBSCH", "breedingIndex": 73, "breedingCategory": 4, "speciesFi": "pajusirkku"}}